xpip_mirror/__init__.py
xpip_mirror/attribute.py
xpip_mirror/cmds.py
xpip_mirror/util.py
xpip_mirror/config/__init__.py
xpip_mirror/config/mirrors.toml
xpip_upload/__init__.py
xpip_upload/attribute.py
xpip_upload/cmds.py
xpip_upload-1.3.1.dist-info/LICENSE
xpip_upload-1.3.1.dist-info/METADATA
xpip_upload-1.3.1.dist-info/WHEEL
xpip_upload-1.3.1.dist-info/entry_points.txt
xpip_upload-1.3.1.dist-info/top_level.txt
xpip_upload-1.3.1.dist-info/zip-safe
xpip_upload-1.3.1.dist-info/RECORD
