Metadata-Version: 2.1
Name: xpip-upload
Version: 1.3.1
Summary: upload python package via twine
Home-page: https://github.com/bondbox/xpip/
Author: Mingzhe Zou
Author-email: zoumingzhe@outlook.com
License: GPLv2
Project-URL: Source Code, https://github.com/bondbox/xpip/
Project-URL: Bug Tracker, https://github.com/bondbox/xpip/issues
Project-URL: Documentation, https://github.com/bondbox/xpip/
Keywords: twine,wheel
Platform: any
Classifier: Programming Language :: Python
Classifier: Programming Language :: Python :: 3
License-File: LICENSE
Requires-Dist: wheel
Requires-Dist: packaging >=24.2
Requires-Dist: twine >=6.1.0
Requires-Dist: keyring
Requires-Dist: keyrings.alt
